aloon/__init__.py
aloon/aloon.py
aloon/argparse_prompt.py
aloon/android_string/__init__.py
aloon/android_string/ordered_set.py
aloon/android_string/string2csv.py
aloon/pack/__init__.py
aloon/pack/build.py
aloon/pack/build_component.py
aloon/pack/config.py
aloon/pack/global_var.py
aloon/pack/init.py
aloon/pack/property.py
aloon/pack/readconfig.py
aloon/pack/config/config.ini
aloon/pack/config/init.ini
aloon/pack/config/shell_config.ini
aloon/pack/shell/build_component.sh
aloon/pack/utils/__init__.py
aloon/pack/utils/replace.py
aloon/pack/utils/utils.py
aloon/simple_parsing/__init__.py
aloon/simple_parsing/conflicts.py
aloon/simple_parsing/docstring.py
aloon/simple_parsing/help_formatter.py
aloon/simple_parsing/logging_utils.py
aloon/simple_parsing/parsing.py
aloon/simple_parsing/utils.py
aloon/simple_parsing/helpers/__init__.py
aloon/simple_parsing/helpers/fields.py
aloon/simple_parsing/helpers/flatten.py
aloon/simple_parsing/helpers/serialization/__init__.py
aloon/simple_parsing/helpers/serialization/decoding.py
aloon/simple_parsing/helpers/serialization/encoding.py
aloon/simple_parsing/helpers/serialization/serializable.py
aloon/simple_parsing/helpers/serialization/yaml_serialization.py
aloon/simple_parsing/wrappers/__init__.py
aloon/simple_parsing/wrappers/dataclass_wrapper.py
aloon/simple_parsing/wrappers/field_metavar.py
aloon/simple_parsing/wrappers/field_parsing.py
aloon/simple_parsing/wrappers/field_wrapper.py
aloon/simple_parsing/wrappers/wrapper.py
aloon/utils/file_utils.py
aloon-1.1.2.dist-info/LICENSE
aloon-1.1.2.dist-info/METADATA
aloon-1.1.2.dist-info/WHEEL
aloon-1.1.2.dist-info/entry_points.txt
aloon-1.1.2.dist-info/namespace_packages.txt
aloon-1.1.2.dist-info/top_level.txt
aloon-1.1.2.dist-info/RECORD
